Workbook

Sheet Methodology
A1: Units Sold vs. Contribution Margin — Weighted CM Analysis
A2: Prepared for Full Circle Brewing / FCB Brands — one-time spreadsheet analysis
A5: TASK (as given):
A6: "Export from ekos a report that shows units sold, for the last two years, by products, then be able to
A7: compare it to our margins, and get a weighted CM. Remove excise tax, add to the bottom."
A8: Updated per follow-up: only the products priced on the Contribution Margin page are kept; labor cost
A9: and excise tax are both fully excluded from every cost figure (not just shown side-by-side); refreshed
A10: again with a current Ekos export so the window is the actual last two years as of today, not 2023-2024.
A12: SOURCE DATA
A13: - Ekos units-sold export: uploaded file "Export_09092026075110_.xls" — a summary report Ekos itself
A14: filtered to [Invoice].Delivery Date BETWEEN 09/09/2024 and 09/09/2026 (i.e. the last two years as of
A15: the date this was built), excluding Item Class = Item Deposits. One row per item, already totaled
... A59: review the 'Ekos Matched' tab to confirm nothing was mis-matched before relying on the totals.

Sheet CM Reference
A1: Key | B1: Company | C1: Brand | D1: Package | E1: Yield (units/batch) | F1: Pkg Cost ($) | G1: Ing Cost ($) | H1: Shipping ($) | I1: Revenue per CE ($) | J1: Total Batch Cost ($) | K1: Total Cost per CE ($) | L1: CM per CE ($) | M1: Margin %
A2: Full Circle Brewing||Capt Hazy||4pack | B2: Full Circle Brewing | C2: Capt Hazy | D2: 4pk 16oz | E2: 258 | F2: 2871.54 | G2: 3143.96 | H2: 0 | I2: 33.99 | J2: =F2+G2+H2 -> 6015.5 | K2: =J2/344.5 -> 17.461538 | L2: =I2-K2 -> 16.528462 | M2: =IFERROR(L2/I2,0) -> 0.48627424
A3: Full Circle Brewing||Capt Hazy||half | B3: Full Circle Brewing | C3: Capt Hazy | D3: 1/2 bbl (Keg) | E3: 50 | F3: 0 | G3: 3143.96 | H3: 0 | I3: 20.75 | J3: =F3+G3+H3 -> 3143.96 | K3: =J3/344.5 -> 9.1261538 | L3: =I3-K3 -> 11.623846 | M3: =IFERROR(L3/I3,0) -> 0.56018536
A4: Full Circle Brewing||Capt Hazy||single | B4: Full Circle Brewing | C4: Capt Hazy | D4: Single 19.2oz | E4: 431 | F4: 2573.07 | G4: 3143.96 | H4: 0 | I4: 30.62 | J4: =F4+G4+H4 -> 5717.03 | K4: =J4/344.5 -> 16.595152 | L4: =I4-K4 -> 14.024848 | M4: =IFERROR(L4/I4,0) -> 0.45802899
A5: Full Circle Brewing||Capt Hazy||sixth | B5: Full Circle Brewing | C5: Capt Hazy | D5: 1/6 bbl (Keg) | E5: 150 | F5: 0 | G5: 3143.96 | H5: 0 | I5: 31.13 | J5: =F5+G5+H5 -> 3143.96 | K5: =J5/344.5 -> 9.1261538 | L5: =I5-K5 -> 22.003846 | M5: =IFERROR(L5/I5,0) -> 0.70683733
A6: Full Circle Brewing||Capt WC IPA||4pack | B6: Full Circle Brewing | C6: Capt WC IPA | D6: 4pk 16oz | E6: 258 | F6: 2871.54 | G6: 2260.01 | H6: 0 | I6: 33.99 | J6: =F6+G6+H6 -> 5131.55 | K6: =J6/344.5 -> 14.895646 | L6: =I6-K6 -> 19.094354 | M6: =IFERROR(L6/I6,0) -> 0.56176388
A7: Full Circle Brewing||Capt WC IPA||half | B7: Full Circle Brewing | C7: Capt WC IPA | D7: 1/2 bbl (Keg) | E7: 50 | F7: 0 | G7: 2260.01 | H7: 0 | I7: 20.76 | J7: =F7+G7+H7 -> 2260.01 | K7: =J7/344.5 -> 6.5602612 | L7: =I7-K7 -> 14.199739 | M7: =IFERROR(L7/I7,0) -> 0.68399512
A8: Full Circle Brewing||Capt WC IPA||single | B8: Full Circle Brewing | C8: Capt WC IPA | D8: Single 19.2oz | E8: 431 | F8: 2573.07 | G8: 2260.01 | H8: 0 | I8: 30.62 | J8: =F8+G8+H8 -> 4833.08 | K8: =J8/344.5 -> 14.02926 | L8: =I8-K8 -> 16.59074 | M8: =IFERROR(L8/I8,0) -> 0.54182692
A9: Full Circle Brewing||Capt WC IPA||sixth | B9: Full Circle Brewing | C9: Capt WC IPA | D9: 1/6 bbl (Keg) | E9: 150 | F9: 0 | G9: 2260.01 | H9: 0 | I9: 31.14 | J9: =F9+G9+H9 -> 2260.01 | K9: =J9/344.5 -> 6.5602612 | L9: =I9-K9 -> 24.579739 | M9: =IFERROR(L9/I9,0) -> 0.78933008
A10: Full Circle Brewing||Peachy Vibes||6pk | B10: Full Circle Brewing | C10: Peachy Vibes | D10: 6pk 12oz | E10: 344 | F10: 3333.36 | G10: 2213.47 | H10: 0 | I10: 27.25 | J10: =F10+G10+H10 -> 5546.83 | K10: =J10/344.5 -> 16.101103 | L10: =I10-K10 -> 11.148897 | M10: =IFERROR(L10/I10,0) -> 0.40913383
A11: Full Circle Brewing||Peachy Vibes||half | B11: Full Circle Brewing | C11: Peachy Vibes | D11: 1/2 bbl (Keg) | E11: 50 | F11: 0 | G11: 2213.47 | H11: 0 | I11: 19.59 | J11: =F11+G11+H11 -> 2213.47 | K11: =J11/344.5 -> 6.4251669 | L11: =I11-K11 -> 13.164833 | M11: =IFERROR(L11/I11,0) -> 0.67201802
A12: Full Circle Brewing||Peachy Vibes||single | B12: Full Circle Brewing | C12: Peachy Vibes | D12: Single 19.2oz | E12: 431 | F12: 2573.07 | G12: 2213.47 | H12: 0 | I12: 30.62 | J12: =F12+G12+H12 -> 4786.54 | K12: =J12/344.5 -> 13.894165 | L12: =I12-K12 -> 16.725835 | M12: =IFERROR(L12/I12,0) -> 0.54623888
A13: Full Circle Brewing||Peachy Vibes||sixth | B13: Full Circle Brewing | C13: Peachy Vibes | D13: 1/6 bbl (Keg) | E13: 150 | F13: 0 | G13: 2213.47 | H13: 0 | I13: 26.56 | J13: =F13+G13+H13 -> 2213.47 | K13: =J13/344.5 -> 6.4251669 | L13: =I13-K13 -> 20.134833 | M13: =IFERROR(L13/I13,0) -> 0.7580886
... A39: Sonoma Cider||The Hatchet||sixth | B39: Sonoma Cider | C39: The Hatchet | D39: 1/6 bbl (Keg) | E39: 150 | F39: 0 | G39: 3476.01 | H39: 0 | I39: 31.35 | J39: =F39+G39+H39 -> 3476.01 | K39: =J39/344.5 -> 10.090015 | L39: =I39-K39 -> 21.259985 | M39: =IFERROR(L39/I39,0) -> 0.67814946

Sheet Ekos Matched
A1: Key | B1: Company | C1: Brand | D1: Package | E1: CE Sold (2-yr) | F1: Qty Sold (2-yr, raw Ekos units) | G1: # Ekos Rows Combined | H1: Ekos Item Name(s) Matched
A2: Full Circle Brewing||Capt Hazy||4pack | B2: Full Circle Brewing | C2: Capt Hazy | D2: 4pk 16oz | E2: 5561.405 | F2: 4165 | G2: 1 | H2: Capt. Save A Hop HAZY IPA (Case - 6x4 - 16oz - Can)
A3: Full Circle Brewing||Capt Hazy||half | B3: Full Circle Brewing | C3: Capt Hazy | D3: 1/2 bbl (Keg) | E3: 1846.52 | F3: 268 | G3: 1 | H3: Capt. Save A Hop HAZY IPA (Keg - 1/2 bbl)
A4: Full Circle Brewing||Capt Hazy||single | B4: Full Circle Brewing | C4: Capt Hazy | D4: Single 19.2oz | E4: 493.9698 | F4: 618 | G4: 1 | H4: Capt. Save A Hop HAZY IPA (Case - 12x - 19.2oz - Can)
A5: Full Circle Brewing||Capt Hazy||sixth | B5: Full Circle Brewing | C5: Capt Hazy | D5: 1/6 bbl (Keg) | E5: 461.63 | F5: 201 | G5: 1 | H5: Capt. Save A Hop HAZY IPA (Keg - 1/6 bbl)
A6: Full Circle Brewing||Capt WC IPA||4pack | B6: Full Circle Brewing | C6: Capt WC IPA | D6: 4pk 16oz | E6: 1188.3915 | F6: 890 | G6: 1 | H6: Capt. Save A Hop WC IPA (Case - 6x4 - 16oz - Can)
A7: Full Circle Brewing||Capt WC IPA||half | B7: Full Circle Brewing | C7: Capt WC IPA | D7: 1/2 bbl (Keg) | E7: 1102.4 | F7: 160 | G7: 1 | H7: Capt. Save A Hop WC IPA (Keg - 1/2 bbl)
A8: Full Circle Brewing||Capt WC IPA||single | B8: Full Circle Brewing | C8: Capt WC IPA | D8: Single 19.2oz | E8: 227.0023 | F8: 284 | G8: 1 | H8: Capt. Save A Hop WC IPA (Case - 12x - 19.2oz - Can)
A9: Full Circle Brewing||Capt WC IPA||sixth | B9: Full Circle Brewing | C9: Capt WC IPA | D9: 1/6 bbl (Keg) | E9: 222.7767 | F9: 97 | G9: 1 | H9: Capt. Save A Hop WC IPA (Keg - 1/6 bbl)
A10: Full Circle Brewing||Peachy Vibes||6pk | B10: Full Circle Brewing | C10: Peachy Vibes | D10: 6pk 12oz | E10: 1643.3852 | F10: 1641 | G10: 1 | H10: Peachy Vibes (Case - 4x6 - 12oz - Can)
A11: Full Circle Brewing||Peachy Vibes||half | B11: Full Circle Brewing | C11: Peachy Vibes | D11: 1/2 bbl (Keg) | E11: 1577.81 | F11: 229 | G11: 1 | H11: Peachy Vibes (Keg - 1/2 bbl)
A12: Full Circle Brewing||Peachy Vibes||single | B12: Full Circle Brewing | C12: Peachy Vibes | D12: Single 19.2oz | E12: 493.9698 | F12: 618 | G12: 1 | H12: Peachy Vibes (Case - 12x - 19.2oz - Can)
A13: Full Circle Brewing||Peachy Vibes||sixth | B13: Full Circle Brewing | C13: Peachy Vibes | D13: 1/6 bbl (Keg) | E13: 773.9767 | F13: 337 | G13: 1 | H13: Peachy Vibes (Keg - 1/6 bbl)
... A39: Sonoma Cider||The Hatchet||sixth | B39: Sonoma Cider | C39: The Hatchet | D39: 1/6 bbl (Keg) | E39: 50.5267 | F39: 22 | G39: 1 | H39: The Hatchet - Apple Cider (Keg - 1/6 bbl)

Sheet Weighted CM Summary
A1: Company | B1: Brand | C1: Package | D1: CE Sold (2-yr) | E1: Revenue per CE ($) | F1: CM per CE ($) | G1: Weighted CM $ | H1: Weighted Revenue $
A2: Full Circle Brewing | B2: Capt Hazy | C2: 4pk 16oz | D2: ='Ekos Matched'!E2 -> 5561.405 | E2: ='CM Reference'!I2 -> 33.99 | F2: ='CM Reference'!L2 -> 16.528462 | G2: =D2*F2 -> 91921.469 | H2: =D2*E2 -> 189032.16
A3: Full Circle Brewing | B3: Capt Hazy | C3: 1/2 bbl (Keg) | D3: ='Ekos Matched'!E3 -> 1846.52 | E3: ='CM Reference'!I3 -> 20.75 | F3: ='CM Reference'!L3 -> 11.623846 | G3: =D3*F3 -> 21463.664 | H3: =D3*E3 -> 38315.29
A4: Full Circle Brewing | B4: Capt Hazy | C4: Single 19.2oz | D4: ='Ekos Matched'!E4 -> 493.9698 | E4: ='CM Reference'!I4 -> 30.62 | F4: ='CM Reference'!L4 -> 14.024848 | G4: =D4*F4 -> 6927.8512 | H4: =D4*E4 -> 15125.355
A5: Full Circle Brewing | B5: Capt Hazy | C5: 1/6 bbl (Keg) | D5: ='Ekos Matched'!E5 -> 461.63 | E5: ='CM Reference'!I5 -> 31.13 | F5: ='CM Reference'!L5 -> 22.003846 | G5: =D5*F5 -> 10157.636 | H5: =D5*E5 -> 14370.542
A6: Full Circle Brewing | B6: Capt WC IPA | C6: 4pk 16oz | D6: ='Ekos Matched'!E6 -> 1188.3915 | E6: ='CM Reference'!I6 -> 33.99 | F6: ='CM Reference'!L6 -> 19.094354 | G6: =D6*F6 -> 22691.568 | H6: =D6*E6 -> 40393.427
A7: Full Circle Brewing | B7: Capt WC IPA | C7: 1/2 bbl (Keg) | D7: ='Ekos Matched'!E7 -> 1102.4 | E7: ='CM Reference'!I7 -> 20.76 | F7: ='CM Reference'!L7 -> 14.199739 | G7: =D7*F7 -> 15653.792 | H7: =D7*E7 -> 22885.824
A8: Full Circle Brewing | B8: Capt WC IPA | C8: Single 19.2oz | D8: ='Ekos Matched'!E8 -> 227.0023 | E8: ='CM Reference'!I8 -> 30.62 | F8: ='CM Reference'!L8 -> 16.59074 | G8: =D8*F8 -> 3766.1362 | H8: =D8*E8 -> 6950.8104
A9: Full Circle Brewing | B9: Capt WC IPA | C9: 1/6 bbl (Keg) | D9: ='Ekos Matched'!E9 -> 222.7767 | E9: ='CM Reference'!I9 -> 31.14 | F9: ='CM Reference'!L9 -> 24.579739 | G9: =D9*F9 -> 5475.7931 | H9: =D9*E9 -> 6937.2664
A10: Full Circle Brewing | B10: Peachy Vibes | C10: 6pk 12oz | D10: ='Ekos Matched'!E10 -> 1643.3852 | E10: ='CM Reference'!I10 -> 27.25 | F10: ='CM Reference'!L10 -> 11.148897 | G10: =D10*F10 -> 18321.932 | H10: =D10*E10 -> 44782.247
A11: Full Circle Brewing | B11: Peachy Vibes | C11: 1/2 bbl (Keg) | D11: ='Ekos Matched'!E11 -> 1577.81 | E11: ='CM Reference'!I11 -> 19.59 | F11: ='CM Reference'!L11 -> 13.164833 | G11: =D11*F11 -> 20771.605 | H11: =D11*E11 -> 30909.298
A12: Full Circle Brewing | B12: Peachy Vibes | C12: Single 19.2oz | D12: ='Ekos Matched'!E12 -> 493.9698 | E12: ='CM Reference'!I12 -> 30.62 | F12: ='CM Reference'!L12 -> 16.725835 | G12: =D12*F12 -> 8262.0571 | H12: =D12*E12 -> 15125.355
A13: Full Circle Brewing | B13: Peachy Vibes | C13: 1/6 bbl (Keg) | D13: ='Ekos Matched'!E13 -> 773.9767 | E13: ='CM Reference'!I13 -> 26.56 | F13: ='CM Reference'!L13 -> 20.134833 | G13: =D13*F13 -> 15583.892 | H13: =D13*E13 -> 20556.821
... A39: Sonoma Cider | B39: The Hatchet | C39: 1/6 bbl (Keg) | D39: ='Ekos Matched'!E39 -> 50.5267 | E39: ='CM Reference'!I39 -> 31.35 | F39: ='CM Reference'!L39 -> 21.259985 | G39: =D39*F39 -> 1074.1969 | H39: =D39*E39 -> 1584.012
A40: TOTAL / WEIGHTED AVERAGE | D40: =SUM(D2:D39) -> 43116.462 | E40: =IFERROR(H40/D40,0) -> 27.353347 | F40: =IFERROR(G40/D40,0) -> 16.081482 | G40: =SUM(G2:G39) -> 693376.59 | H40: =SUM(H2:H39) -> 1179379.5
A42: Blended margin % | E42: =IFERROR(F40/E40,0) -> 0.58791642
A44: CE Sold pulled from 'Ekos Matched' (Ekos Delivery Date 09/09/2024..09/09/2026). CM per CE pulled from 'CM Reference' (labor cost and excise tax excluded from every cost figure). Weighted CM $ = CE Sold x CM per CE for each row; the TOTAL row's weighted-average CM per CE is SUM(Weighted CM $) / SUM(CE Sold) across all rows — i.e. volume-weighted, not a simple average of the per-row CM figures.
